{"variantName":"hero-promo","baseBlock":"hero","version":"1.0.0","created":"2026-02-12T04:15:00.000Z","sourceContext":{"originUrl":"https://www.business.att.com/","originPage":"AT&T Business homepage","blockPosition":"lower-middle"},"visualCharacteristics":{"colorScheme":"dark","density":"minimal","purpose":"promotional","imagePattern":"background"},"contentPattern":{"structure":"eyebrow + heading + description + legal + CTA + background-image","buttonCount":1,"imageCount":1},"reuseGuidance":{"suitableFor":["promotional hero sections","guarantee sections"],"notSuitableFor":["light themed heroes","heroes with side images"]},"usage":{"pagesUsing":["content/index"],"reuseCount":1,"lastUsed":"2026-02-12T04:15:00.000Z"}}
